jsonviewertool_cli/__init__.py
jsonviewertool_cli/cli.py
jsonviewertool_cli-0.1.0.dist-info/licenses/LICENSE
jsonviewertool_cli-0.1.0.dist-info/METADATA
jsonviewertool_cli-0.1.0.dist-info/WHEEL
jsonviewertool_cli-0.1.0.dist-info/entry_points.txt
jsonviewertool_cli-0.1.0.dist-info/top_level.txt
jsonviewertool_cli-0.1.0.dist-info/RECORD
